cape_privacy/__init__.py
cape_privacy/coordinator/__init__.py
cape_privacy/coordinator/client.py
cape_privacy/coordinator/client_test.py
cape_privacy/coordinator/auth/__init__.py
cape_privacy/coordinator/auth/api_token.py
cape_privacy/coordinator/auth/api_token_test.py
cape_privacy/coordinator/utils/__init__.py
cape_privacy/coordinator/utils/base64.py
cape_privacy/coordinator/utils/base64_test.py
cape_privacy/pandas/__init__.py
cape_privacy/pandas/dtypes.py
cape_privacy/pandas/registry.py
cape_privacy/pandas/registry_test.py
cape_privacy/pandas/transformer.py
cape_privacy/pandas/transformations/__init__.py
cape_privacy/pandas/transformations/base.py
cape_privacy/pandas/transformations/column_redact.py
cape_privacy/pandas/transformations/column_redact_test.py
cape_privacy/pandas/transformations/perturbation.py
cape_privacy/pandas/transformations/perturbation_test.py
cape_privacy/pandas/transformations/rounding.py
cape_privacy/pandas/transformations/rounding_test.py
cape_privacy/pandas/transformations/row_redact.py
cape_privacy/pandas/transformations/row_redact_test.py
cape_privacy/pandas/transformations/test_utils.py
cape_privacy/pandas/transformations/tokenizer.py
cape_privacy/pandas/transformations/tokenizer_test.py
cape_privacy/policy/__init__.py
cape_privacy/policy/data.py
cape_privacy/policy/data_test.py
cape_privacy/policy/exceptions.py
cape_privacy/policy/policy.py
cape_privacy/policy/policy_test.py
cape_privacy/policy/policy_test_fixtures.py
cape_privacy/spark/__init__.py
cape_privacy/spark/dtypes.py
cape_privacy/spark/registry.py
cape_privacy/spark/registry_test.py
cape_privacy/spark/transformer.py
cape_privacy/spark/utils.py
cape_privacy/spark/transformations/__init__.py
cape_privacy/spark/transformations/base.py
cape_privacy/spark/transformations/perturbation.py
cape_privacy/spark/transformations/perturbation_test.py
cape_privacy/spark/transformations/redaction.py
cape_privacy/spark/transformations/redaction_test.py
cape_privacy-0.3.0.dist-info/LICENSE
cape_privacy-0.3.0.dist-info/METADATA
cape_privacy-0.3.0.dist-info/NOTICE
cape_privacy-0.3.0.dist-info/WHEEL
cape_privacy-0.3.0.dist-info/top_level.txt
cape_privacy-0.3.0.dist-info/RECORD
